{
  "main": {
    "id": "4c004b498d3ff1ba",
    "type": "split",
    "children": [
      {
        "id": "20e07312d295e337",
        "type": "tabs",
        "children": [
          {
            "id": "154375fad6cf910b",
            "type": "leaf",
            "state": {
              "type": "markdown",
              "state": {
                "file": "File System Forensic Analysis/Part 3. File System Analysis/Chapter 8. File System Analysis.md",
                "mode": "preview",
                "source": true
              },
              "icon": "lucide-file",
              "title": "Chapter 8. File System Analysis"
            }
          }
        ]
      }
    ],
    "direction": "vertical"
  },
  "left": {
    "id": "abfd4dcd443d5bff",
    "type": "split",
    "children": [
      {
        "id": "77d97b6c9723a0b3",
        "type": "tabs",
        "children": [
          {
            "id": "1bf19fb8e457e453",
            "type": "leaf",
            "state": {
              "type": "file-explorer",
              "state": {
                "sortOrder": "alphabetical",
                "autoReveal": false
              },
              "icon": "lucide-folder-closed",
              "title": "Files"
            }
          },
          {
            "id": "cec9a7700ad274a4",
            "type": "leaf",
            "state": {
              "type": "search",
              "state": {
                "query": "",
                "matchingCase": false,
                "explainSearch": false,
                "collapseAll": false,
                "extraContext": false,
                "sortOrder": "alphabetical"
              },
              "icon": "lucide-search",
              "title": "Search"
            }
          },
          {
            "id": "707958c4db7c5926",
            "type": "leaf",
            "state": {
              "type": "bookmarks",
              "state": {},
              "icon": "lucide-bookmark",
              "title": "Bookmarks"
            }
          }
        ]
      }
    ],
    "direction": "horizontal",
    "width": 300
  },
  "right": {
    "id": "1b490e33aebbb892",
    "type": "split",
    "children": [
      {
        "id": "83ca032c4b51bd37",
        "type": "tabs",
        "children": [
          {
            "id": "c890ea866b26d030",
            "type": "leaf",
            "state": {
              "type": "backlink",
              "state": {
                "collapseAll": false,
                "extraContext": false,
                "sortOrder": "alphabetical",
                "showSearch": false,
                "searchQuery": "",
                "backlinkCollapsed": false,
                "unlinkedCollapsed": true
              },
              "icon": "links-coming-in",
              "title": "Backlinks"
            }
          },
          {
            "id": "629f880fe4a1ae23",
            "type": "leaf",
            "state": {
              "type": "outgoing-link",
              "state": {
                "linksCollapsed": false,
                "unlinkedCollapsed": true
              },
              "icon": "links-going-out",
              "title": "Outgoing links"
            }
          },
          {
            "id": "96d8768e9a7766c7",
            "type": "leaf",
            "state": {
              "type": "tag",
              "state": {
                "sortOrder": "frequency",
                "useHierarchy": true,
                "showSearch": false,
                "searchQuery": ""
              },
              "icon": "lucide-tags",
              "title": "Tags"
            }
          },
          {
            "id": "2ec3e21ef51c174c",
            "type": "leaf",
            "state": {
              "type": "all-properties",
              "state": {
                "sortOrder": "frequency",
                "showSearch": false,
                "searchQuery": ""
              },
              "icon": "lucide-archive",
              "title": "All properties"
            }
          },
          {
            "id": "f771ea239d835adb",
            "type": "leaf",
            "state": {
              "type": "outline",
              "state": {
                "followCursor": false,
                "showSearch": false,
                "searchQuery": ""
              },
              "icon": "lucide-list",
              "title": "Outline"
            }
          }
        ]
      }
    ],
    "direction": "horizontal",
    "width": 300,
    "collapsed": true
  },
  "left-ribbon": {
    "hiddenItems": {
      "switcher:Open quick switcher": false,
      "graph:Open graph view": false,
      "canvas:Create new canvas": false,
      "daily-notes:Open today's daily note": false,
      "templates:Insert template": false,
      "command-palette:Open command palette": false,
      "bases:Create new base": false
    }
  },
  "active": "1bf19fb8e457e453",
  "lastOpenFiles": [
    "File System Forensic Analysis/Part 3. File System Analysis/Chapter 8. File System Analysis.md~",
    "File System Forensic Analysis/etc/journaling data changes.md",
    "File System Forensic Analysis/etc/data carving with no footer.md",
    "File System Forensic Analysis/Part 3. File System Analysis/Chapter 8. File System Analysis.md",
    "File System Forensic Analysis/Images/further sync issues.png",
    "File System Forensic Analysis/Images/filename metadata sync issue.png",
    "File System Forensic Analysis/Images/metadata structure parsing for file.png",
    "File System Forensic Analysis/Images/mactime output.png",
    "File System Forensic Analysis/etc/Data analysis layers.md",
    "File System Forensic Analysis/Part 1. Foundations/Chapter 1. Digital Investigation.md",
    "File System Forensic Analysis/etc/Disk as layers of abstraction.md",
    "File System Forensic Analysis/Images/metadata entry sync issues.png",
    "File System Forensic Analysis/Images/logical file address demo.png",
    "File System Forensic Analysis/Images/logical file system address demo.png",
    "File System Forensic Analysis/Images/data category interaction.png",
    "File System Forensic Analysis/Part 2. Volume Analysis/Chapter 6. Server-based Partitions.md",
    "File System Forensic Analysis/Part 3. File System Analysis",
    "File System Forensic Analysis/Part 2. Volume Analysis/Chapter 6. Server-based Partitions.md~",
    "File System Forensic Analysis/Part 2. Volume Analysis/4913",
    "Digital Forensics Concepts/File System.md",
    "File System Forensic Analysis/Part 2. Volume Analysis/Chapter 5. PC-based Partitions.md",
    "File System Forensic Analysis/Part 2. Volume Analysis/Chapter 5. PC-based Partitions.md~",
    "Digital Forensics Concepts/DOS (MBR) partitioning/Extended Boot Record.md",
    "Digital Forensics Concepts/DOS (MBR) partitioning/Primary Extended Partition.md",
    "Digital Forensics Concepts/Partition System.md",
    "Digital Forensics Concepts/NTFS/References.md",
    "Digital Forensics Concepts/NTFS/Partition Boot Sector.md",
    "File System Forensic Analysis/Images/extended partition table entry.png",
    "File System Forensic Analysis/Images/EBR partition table second entry.png",
    "File System Forensic Analysis/Part 2. Volume Analysis/Chapter 4. Volume Analysis.md",
    "File System Forensic Analysis/Part 2. Volume Analysis/Chapter 4. Volume Analysis.md~",
    "File System Forensic Analysis/etc/sector copy data loss.md",
    "File System Forensic Analysis/etc/ATA and SCSI disk size limitations.md",
    "Digital Forensics Concepts/DOS (MBR) partitioning",
    "Digital Forensics Concepts",
    "File System Forensic Analysis/Part 1. Foundations/Chapter 3. Hard Disk Data Acquisition.md",
    "File System Forensic Analysis/Part 1. Foundations/Chapter 2. Computer Foundations.md",
    "File System Forensic Analysis/Part 2. Volume Analysis",
    "File System Forensic Analysis/Part 1/Chapter 3. Hard Disk Data Acquisition.md~",
    "Welcome.md"
  ]
}